packaging_demo/__init__.py
packaging_demo/cities.json
packaging_demo/states_info.py
generated_python_packaging_demo-0.0.0.dist-info/METADATA
generated_python_packaging_demo-0.0.0.dist-info/WHEEL
generated_python_packaging_demo-0.0.0.dist-info/top_level.txt
generated_python_packaging_demo-0.0.0.dist-info/RECORD
